ether_ghost/__init__.py
ether_ghost/__main__.py
ether_ghost/api/__init__.py
ether_ghost/api/base.py
ether_ghost/api/connector.py
ether_ghost/api/forward_proxy.py
ether_ghost/api/session.py
ether_ghost/api/sessiontype.py
ether_ghost/api/settings.py
ether_ghost/api/utils.py
ether_ghost/core/__init__.py
ether_ghost/core/base.py
ether_ghost/core/custom_encoders.py
ether_ghost/core/exceptions.py
ether_ghost/core/php_decoder.py
ether_ghost/core/php_session_common.py
ether_ghost/file_transfer_status.py
ether_ghost/main.py
ether_ghost/public/assets/MapleMono-NF-Regular-BgE8BQz8.ttf
ether_ghost/public/assets/MapleMono-NF-SemiBold-D91h6FBp.ttf
ether_ghost/public/assets/index-CYKTApce.css
ether_ghost/public/assets/index-DGNoZk-a.js
ether_ghost/public/assets/logo-Cv1N-hgL.svg
ether_ghost/public/favicon.ico
ether_ghost/public/index.html
ether_ghost/session_connector.py
ether_ghost/session_connectors/__init__.py
ether_ghost/session_connectors/reverse_shell.py
ether_ghost/session_manager.py
ether_ghost/session_types.py
ether_ghost/sessions/Payload.class
ether_ghost/sessions/Payload.java
ether_ghost/sessions/__init__.py
ether_ghost/sessions/jsp_behinder.py
ether_ghost/sessions/linux_cmd_oneliner.py
ether_ghost/sessions/php_behinder.py
ether_ghost/sessions/php_etherghost.py
ether_ghost/sessions/php_oneliner.py
ether_ghost/sessions/php_raw.py
ether_ghost/sessions/reverse_shell.py
ether_ghost/tcp_proxies.py
ether_ghost/utils/__init__.py
ether_ghost/utils/cipher.py
ether_ghost/utils/const.py
ether_ghost/utils/db.py
ether_ghost/utils/eng_words_map.json
ether_ghost/utils/nodejs_bridge.py
ether_ghost/utils/phone_5.json
ether_ghost/utils/random_data.py
ether_ghost/utils/tools.py
ether_ghost/utils/user_agents.py
ether_ghost/vessel_php/__init__.py
ether_ghost/vessel_php/client.php
ether_ghost/vessel_php/main.py
ether_ghost/vessel_php/server.php
ether_ghost-0.2.2.dist-info/LICENSE
ether_ghost-0.2.2.dist-info/METADATA
ether_ghost-0.2.2.dist-info/WHEEL
ether_ghost-0.2.2.dist-info/entry_points.txt
ether_ghost-0.2.2.dist-info/RECORD
