Metadata-Version: 2.3
Name: ether_ghost
Version: 0.2.2
Summary: 
Author: Marven11
Author-email: 110723864+Marven11@users.noreply.github.com
Requires-Python: >=3.8,<4.0
Classifier: Programming Language :: Python :: 3
Classifier: Programming Language :: Python :: 3.8
Classifier: Programming Language :: Python :: 3.9
Classifier: Programming Language :: Python :: 3.10
Classifier: Programming Language :: Python :: 3.11
Classifier: Programming Language :: Python :: 3.12
Classifier: Programming Language :: Python :: 3.13
Requires-Dist: chardet (>=5.2.0,<6.0.0)
Requires-Dist: fastapi
Requires-Dist: httpx[socks]
Requires-Dist: pycryptodome
Requires-Dist: pydantic (>=2,<3)
Requires-Dist: python-multipart
Requires-Dist: requests
Requires-Dist: sqlalchemy
Requires-Dist: sqlalchemy-utils
Requires-Dist: uvicorn
